<?xml version="1.0" encoding="UTF-8"?>
<man:metadata
   xmlns:man="https://www.lancaster.ac.uk/library/ns/digital-library/manifest/1"
   xmlns:tei="http://www.tei-c.org/ns/1.0"
>
  <man:meta id="MS-DAVY-12203">
    <author id="humphry_davy" href="authors"/>
    <binding>Marbled hard cover, dark red spine and corners</binding>
    <foliation/>
    <hand/>
    <height>9.25in</height>
    <id>RI MS HD/22/C</id>
    <origDate>
      <tei:origDate notBefore="1805-01-01" notAfter="1805-12-31">1805</tei:origDate>
    </origDate>
    <pages>148, 1+4 loose leaves</pages>
    <provenance>Royal Institution</provenance>
    <summary>Notebook containing scientific and philosophical notes, and poetry</summary>
    <title>RI MS HD/22/C</title>
    <width>7.25in</width>
    <contents><!--
      <tei:msItem>
        <tei:locus from="" to=""/>
        <tei:title></tei:title>
      </tei:msItem>
    --></contents>
  </man:meta>
</man:metadata>
