{
  "5": {
    "persons": [
      {
        "name": "Onuphrio",
        "birth": null,
        "death": null,
        "description": "Onuphiro is the name of a fictional character in the dialogues of Davy's Consolations in Travel. The anglicized version of the name is Humphry.",
        "id": "person_108"
      },
      {
        "name": "Ambrosio",
        "birth": null,
        "death": null,
        "description": "A fictional character in Humphry Davy's Consolations in Travel (1830).",
        "id": "person_101"
      }
    ],
    "places": [
      {
        "name": "The Colosseum",
        "description": "The Colosseum, the largest amphitheatre ever built, is located in the centre of Rome. Now a ruin, its construction began 2,000 years ago.",
        "id": "place_199"
      },
      {
        "name": "Bay of Naples",
        "description": "The Bay (or Gulf) of Naples is located on the south-western coast of Italy, with Naples to the north, Vesuvius to the east, and the Sorrento Peninsula to the south.",
        "id": "place_704"
      },
      {
        "name": "Naples",
        "description": "Naples is the regional capital of Campania in Italy. It is located beneath the volcano, Vesuvius.",
        "id": "place_156"
      },
      {
        "name": "Rome",
        "description": "The capital of Italy.",
        "id": "place_155"
      }
    ]
  },
  "6": {
    "persons": [
      {
        "name": "Philalethes",
        "birth": null,
        "death": null,
        "description": "A fictional character in Humphry Davy's Consolations in Travel (1830).",
        "id": "person_102"
      }
    ]
  },
  "7": {},
  "8": {
    "persons": [
      {
        "name": "Ambrosio",
        "birth": null,
        "death": null,
        "description": "A fictional character in Humphry Davy's Consolations in Travel (1830).",
        "id": "person_101"
      }
    ]
  },
  "9": {
    "places": [
      {
        "name": "Palermo",
        "description": "A city in Sicily, Italy.",
        "id": "place_1159"
      }
    ]
  },
  "10": {
    "persons": [
      {
        "name": "Philalethes",
        "birth": null,
        "death": null,
        "description": "A fictional character in Humphry Davy's Consolations in Travel (1830).",
        "id": "person_102"
      }
    ],
    "places": [
      {
        "name": "Naples",
        "description": "Naples is the regional capital of Campania in Italy. It is located beneath the volcano, Vesuvius.",
        "id": "place_156"
      }
    ]
  },
  "11": {
    "persons": [
      {
        "name": "Philalethes",
        "birth": null,
        "death": null,
        "description": "A fictional character in Humphry Davy's Consolations in Travel (1830).",
        "id": "person_102"
      },
      {
        "name": "Onuphrio",
        "birth": null,
        "death": null,
        "description": "Onuphiro is the name of a fictional character in the dialogues of Davy's Consolations in Travel. The anglicized version of the name is Humphry.",
        "id": "person_108"
      }
    ],
    "places": [
      {
        "name": "Mount Somma",
        "description": "A mountain located in the Province of Naples, in the Campania region of southern Italy. It has a collapsed caldera of an older volcano, with Mount Vesuvius rising up from the center.",
        "id": "place_1169"
      },
      {
        "name": "Portici",
        "description": "A town and comune of the Metropolitan City of Naples in Italy",
        "id": "place_413"
      }
    ]
  },
  "12": {
    "persons": [
      {
        "name": "Onuphrio",
        "birth": null,
        "death": null,
        "description": "Onuphiro is the name of a fictional character in the dialogues of Davy's Consolations in Travel. The anglicized version of the name is Humphry.",
        "id": "person_108"
      }
    ],
    "places": [
      {
        "name": "Portici",
        "description": "A town and comune of the Metropolitan City of Naples in Italy",
        "id": "place_413"
      },
      {
        "name": "Herculaneum",
        "description": "Herculaneum was an ancient Roman town, located in the modern-day comune of Ercolano, Campania, Italy.",
        "id": "place_714"
      }
    ]
  },
  "13": {
    "persons": [
      {
        "name": "Ambrosio",
        "birth": null,
        "death": null,
        "description": "A fictional character in Humphry Davy's Consolations in Travel (1830).",
        "id": "person_101"
      },
      {
        "name": "Onuphrio",
        "birth": null,
        "death": null,
        "description": "Onuphiro is the name of a fictional character in the dialogues of Davy's Consolations in Travel. The anglicized version of the name is Humphry.",
        "id": "person_108"
      }
    ],
    "places": [
      {
        "name": "The Colosseum",
        "description": "The Colosseum, the largest amphitheatre ever built, is located in the centre of Rome. Now a ruin, its construction began 2,000 years ago.",
        "id": "place_199"
      }
    ]
  },
  "14": {
    "persons": [
      {
        "name": "Ambrosio",
        "birth": null,
        "death": null,
        "description": "A fictional character in Humphry Davy's Consolations in Travel (1830).",
        "id": "person_101"
      }
    ],
    "places": [
      {
        "name": "The Colosseum",
        "description": "The Colosseum, the largest amphitheatre ever built, is located in the centre of Rome. Now a ruin, its construction began 2,000 years ago.",
        "id": "place_199"
      }
    ]
  },
  "15": {
    "persons": [
      {
        "name": "Philalethes",
        "birth": null,
        "death": null,
        "description": "A fictional character in Humphry Davy's Consolations in Travel (1830).",
        "id": "person_102"
      },
      {
        "name": "Onuphrio",
        "birth": null,
        "death": null,
        "description": "Onuphiro is the name of a fictional character in the dialogues of Davy's Consolations in Travel. The anglicized version of the name is Humphry.",
        "id": "person_108"
      },
      {
        "name": "JakobBöhme",
        "birth": "",
        "death": "",
        "description": "(Jacob Behman), a German philosopher, Christian mystic, and Lutheran Protestant theologian.",
        "id": "person_935"
      },
      {
        "name": "Muhammad",
        "birth": "",
        "death": "",
        "description": "The Holy Prophet and founder of Islam.",
        "id": "person_114"
      }
    ]
  },
  "16": {
    "persons": [
      {
        "name": "Philalethes",
        "birth": null,
        "death": null,
        "description": "A fictional character in Humphry Davy's Consolations in Travel (1830).",
        "id": "person_102"
      },
      {
        "name": "Ambrosio",
        "birth": null,
        "death": null,
        "description": "A fictional character in Humphry Davy's Consolations in Travel (1830).",
        "id": "person_101"
      }
    ]
  },
  "17": {
    "persons": [
      {
        "name": "Philalethes",
        "birth": null,
        "death": null,
        "description": "A fictional character in Humphry Davy's Consolations in Travel (1830).",
        "id": "person_102"
      },
      {
        "name": "Onuphrio",
        "birth": null,
        "death": null,
        "description": "Onuphiro is the name of a fictional character in the dialogues of Davy's Consolations in Travel. The anglicized version of the name is Humphry.",
        "id": "person_108"
      }
    ]
  },
  "18": {},
  "19": {
    "persons": [
      {
        "name": "Onuphrio",
        "birth": null,
        "death": null,
        "description": "Onuphiro is the name of a fictional character in the dialogues of Davy's Consolations in Travel. The anglicized version of the name is Humphry.",
        "id": "person_108"
      }
    ]
  },
  "20": {
    "persons": [
      {
        "name": "Philalethes",
        "birth": null,
        "death": null,
        "description": "A fictional character in Humphry Davy's Consolations in Travel (1830).",
        "id": "person_102"
      },
      {
        "name": "Ambrosio",
        "birth": null,
        "death": null,
        "description": "A fictional character in Humphry Davy's Consolations in Travel (1830).",
        "id": "person_101"
      }
    ],
    "places": [
      {
        "name": "The Colosseum",
        "description": "The Colosseum, the largest amphitheatre ever built, is located in the centre of Rome. Now a ruin, its construction began 2,000 years ago.",
        "id": "place_199"
      }
    ]
  },
  "21": {
    "persons": [
      {
        "name": "Ambrosio",
        "birth": null,
        "death": null,
        "description": "A fictional character in Humphry Davy's Consolations in Travel (1830).",
        "id": "person_101"
      }
    ],
    "places": [
      {
        "name": "New Holland",
        "description": "New Holland was the name first given to Australia by the Dutch seafarer, Abel Tasman.",
        "id": "place_685"
      },
      {
        "name": "New Zealand",
        "description": "An island country in the southwestern Pacific Ocean.",
        "id": "place_1160"
      }
    ]
  },
  "22": {
    "persons": [
      {
        "name": "Philalethes",
        "birth": null,
        "death": null,
        "description": "A fictional character in Humphry Davy's Consolations in Travel (1830).",
        "id": "person_102"
      }
    ]
  },
  "23": {},
  "24": {},
  "25": {
    "persons": [
      {
        "name": "Ambrosio",
        "birth": null,
        "death": null,
        "description": "A fictional character in Humphry Davy's Consolations in Travel (1830).",
        "id": "person_101"
      }
    ],
    "places": [
      {
        "name": "Rome",
        "description": "The capital of Italy.",
        "id": "place_155"
      },
      {
        "name": "Italy",
        "description": "",
        "id": "place_097"
      },
      {
        "name": "northern coast of Africa",
        "description": "The coastal region of North Africa bounded by Egypt (east), by the Atlantic (west), by the Sahara (south), and by the Mediterranean Sea (north), and now comprising Morocco, Algeria, Tunisia, and Libya.",
        "id": "place_1162"
      }
    ]
  },
  "26": {},
  "27": {},
  "28": {
    "persons": [
      {
        "name": "Titus CaesarVespasianus",
        "birth": "",
        "death": "",
        "description": "Roman emperor from 79 to 81.",
        "id": "person_954"
      },
      {
        "name": "JesusChrist",
        "birth": "",
        "death": "",
        "description": "The central figure of Christianity; a first-century Jewish preacher and religious leader.",
        "id": "person_951"
      }
    ],
    "places": [
      {
        "name": "Jerusalem",
        "description": "Jerusalem is an ancient city in West Asia, on a plateau in the Judaean Mountains between the Mediterranean and the Dead Sea.",
        "id": "place_173"
      }
    ]
  },
  "29": {
    "persons": [
      {
        "name": "Philalethes",
        "birth": null,
        "death": null,
        "description": "A fictional character in Humphry Davy's Consolations in Travel (1830).",
        "id": "person_102"
      },
      {
        "name": "Constantine",
        "birth": "",
        "death": "",
        "description": "Roman emperor from AD 306 to 337; he patronised Christianity and was converted to it on his deathbed.",
        "id": "person_955"
      },
      {
        "name": "Ambrosio",
        "birth": null,
        "death": null,
        "description": "A fictional character in Humphry Davy's Consolations in Travel (1830).",
        "id": "person_101"
      },
      {
        "name": "Onuphrio",
        "birth": null,
        "death": null,
        "description": "Onuphiro is the name of a fictional character in the dialogues of Davy's Consolations in Travel. The anglicized version of the name is Humphry.",
        "id": "person_108"
      }
    ]
  },
  "30": {
    "persons": [
      {
        "name": "Ambrosio",
        "birth": null,
        "death": null,
        "description": "A fictional character in Humphry Davy's Consolations in Travel (1830).",
        "id": "person_101"
      }
    ]
  },
  "31": {
    "persons": [
      {
        "name": "Cain",
        "birth": "",
        "death": "",
        "description": "A biblical figure in the Book of Genesis. He is the firstborn son of Adam and Eve and brother of Abel.",
        "id": "person_956"
      }
    ]
  },
  "32": {
    "persons": [
      {
        "name": "Anaxagoras",
        "birth": "",
        "death": null,
        "description": "Greek Presocratic philosopher.",
        "id": "person_605"
      }
    ]
  },
  "33": {
    "persons": [
      {
        "name": "JesusChrist",
        "birth": "",
        "death": "",
        "description": "The central figure of Christianity; a first-century Jewish preacher and religious leader.",
        "id": "person_951"
      }
    ]
  },
  "34": {
    "places": [
      {
        "name": "Iran",
        "description": "Iran, also known as Persia and officially the Islamic Republic of Iran, is a country located at the crossroads of West, Central and South Asia.",
        "id": "place_873"
      }
    ]
  },
  "35": {
    "persons": [
      {
        "name": "JesusChrist",
        "birth": "",
        "death": "",
        "description": "The central figure of Christianity; a first-century Jewish preacher and religious leader.",
        "id": "person_951"
      },
      {
        "name": "Onuphrio",
        "birth": null,
        "death": null,
        "description": "Onuphiro is the name of a fictional character in the dialogues of Davy's Consolations in Travel. The anglicized version of the name is Humphry.",
        "id": "person_108"
      },
      {
        "name": "Ambrosio",
        "birth": null,
        "death": null,
        "description": "A fictional character in Humphry Davy's Consolations in Travel (1830).",
        "id": "person_101"
      }
    ]
  },
  "36": {
    "works": [
      {
        "name": "Der Messias",
        "author": "Friedrich Gottlieb Klopstock",
        "id": "otherwork_244"
      }
    ]
  },
  "37": {},
  "38": {},
  "39": {},
  "40": {
    "places": [
      {
        "name": "Judaea",
        "description": "The southernmost of the three traditional divisions of ancient Palestine; there are political and religious disputes over what to call this land today.",
        "id": "place_1186"
      }
    ]
  },
  "41": {
    "persons": [
      {
        "name": "DavidHartley",
        "birth": "",
        "death": "",
        "description": "Associationist, whose work argued that the vibrations of nerves created sensation. FRSL.",
        "id": "person_018"
      },
      {
        "name": "JohnLocke",
        "birth": "",
        "death": "",
        "description": "English philosopher and physician, widely regarded as one of the most influential of early Enlightenment thinkers. FRSL.",
        "id": "person_078"
      },
      {
        "name": "IsaacNewton",
        "birth": "",
        "death": "",
        "description": "Prominent English natural philosopher and mathematician greatly admired by Davy who once under the influence of several litres of nitrous oxide wrote in his notebook 'Davy & Newton' in one inch letters. FRSL.",
        "id": "person_036"
      }
    ]
  },
  "42": {
    "persons": [
      {
        "name": "JesusChrist",
        "birth": "",
        "death": "",
        "description": "The central figure of Christianity; a first-century Jewish preacher and religious leader.",
        "id": "person_951"
      }
    ],
    "places": [
      {
        "name": "Judaea",
        "description": "The southernmost of the three traditional divisions of ancient Palestine; there are political and religious disputes over what to call this land today.",
        "id": "place_1186"
      }
    ]
  },
  "43": {
    "persons": [
      {
        "name": "Ambrosio",
        "birth": null,
        "death": null,
        "description": "A fictional character in Humphry Davy's Consolations in Travel (1830).",
        "id": "person_101"
      },
      {
        "name": "Philalethes",
        "birth": null,
        "death": null,
        "description": "A fictional character in Humphry Davy's Consolations in Travel (1830).",
        "id": "person_102"
      },
      {
        "name": "Onuphrio",
        "birth": null,
        "death": null,
        "description": "Onuphiro is the name of a fictional character in the dialogues of Davy's Consolations in Travel. The anglicized version of the name is Humphry.",
        "id": "person_108"
      }
    ]
  },
  "44": {},
  "45": {},
  "46": {
    "persons": [
      {
        "name": "Onuphrio",
        "birth": null,
        "death": null,
        "description": "Onuphiro is the name of a fictional character in the dialogues of Davy's Consolations in Travel. The anglicized version of the name is Humphry.",
        "id": "person_108"
      }
    ]
  },
  "47": {
    "persons": [
      {
        "name": "Ambrosio",
        "birth": null,
        "death": null,
        "description": "A fictional character in Humphry Davy's Consolations in Travel (1830).",
        "id": "person_101"
      }
    ]
  },
  "48": {},
  "49": {},
  "50": {},
  "51": {},
  "52": {},
  "53": {},
  "54": {},
  "55": {
    "persons": [
      {
        "name": "Onuphrio",
        "birth": null,
        "death": null,
        "description": "Onuphiro is the name of a fictional character in the dialogues of Davy's Consolations in Travel. The anglicized version of the name is Humphry.",
        "id": "person_108"
      }
    ]
  },
  "56": {
    "persons": [
      {
        "name": "Ambrosio",
        "birth": null,
        "death": null,
        "description": "A fictional character in Humphry Davy's Consolations in Travel (1830).",
        "id": "person_101"
      }
    ]
  },
  "57": {},
  "58": {},
  "59": {},
  "60": {},
  "61": {
    "persons": [
      {
        "name": "Onuphrio",
        "birth": null,
        "death": null,
        "description": "Onuphiro is the name of a fictional character in the dialogues of Davy's Consolations in Travel. The anglicized version of the name is Humphry.",
        "id": "person_108"
      },
      {
        "name": "Moses",
        "birth": "",
        "death": null,
        "description": "According to the Old Testament Hebrew prophet who is considered the most important prophet in Judaism and one of the most important prophets in Christianity and other religions.",
        "id": "person_115"
      },
      {
        "name": "JesusChrist",
        "birth": "",
        "death": "",
        "description": "The central figure of Christianity; a first-century Jewish preacher and religious leader.",
        "id": "person_951"
      },
      {
        "name": "Muhammad",
        "birth": "",
        "death": "",
        "description": "The Holy Prophet and founder of Islam.",
        "id": "person_114"
      }
    ]
  },
  "62": {
    "persons": [
      {
        "name": "Ambrosio",
        "birth": null,
        "death": null,
        "description": "A fictional character in Humphry Davy's Consolations in Travel (1830).",
        "id": "person_101"
      },
      {
        "name": "JesusChrist",
        "birth": "",
        "death": "",
        "description": "The central figure of Christianity; a first-century Jewish preacher and religious leader.",
        "id": "person_951"
      },
      {
        "name": "Muhammad",
        "birth": "",
        "death": "",
        "description": "The Holy Prophet and founder of Islam.",
        "id": "person_114"
      }
    ]
  },
  "63": {
    "persons": [
      {
        "name": "JesusChrist",
        "birth": "",
        "death": "",
        "description": "The central figure of Christianity; a first-century Jewish preacher and religious leader.",
        "id": "person_951"
      }
    ]
  },
  "64": {
    "persons": [
      {
        "name": "JesusChrist",
        "birth": "",
        "death": "",
        "description": "The central figure of Christianity; a first-century Jewish preacher and religious leader.",
        "id": "person_951"
      }
    ]
  },
  "65": {},
  "66": {
    "persons": [
      {
        "name": "Onuphrio",
        "birth": null,
        "death": null,
        "description": "Onuphiro is the name of a fictional character in the dialogues of Davy's Consolations in Travel. The anglicized version of the name is Humphry.",
        "id": "person_108"
      }
    ]
  },
  "67": {
    "persons": [
      {
        "name": "Moses",
        "birth": "",
        "death": null,
        "description": "According to the Old Testament Hebrew prophet who is considered the most important prophet in Judaism and one of the most important prophets in Christianity and other religions.",
        "id": "person_115"
      }
    ]
  },
  "68": {
    "persons": [
      {
        "name": "Ambrosio",
        "birth": null,
        "death": null,
        "description": "A fictional character in Humphry Davy's Consolations in Travel (1830).",
        "id": "person_101"
      },
      {
        "name": "Moses",
        "birth": "",
        "death": null,
        "description": "According to the Old Testament Hebrew prophet who is considered the most important prophet in Judaism and one of the most important prophets in Christianity and other religions.",
        "id": "person_115"
      },
      {
        "name": "JesusChrist",
        "birth": "",
        "death": "",
        "description": "The central figure of Christianity; a first-century Jewish preacher and religious leader.",
        "id": "person_951"
      }
    ]
  },
  "69": {
    "persons": [
      {
        "name": "Moses",
        "birth": "",
        "death": null,
        "description": "According to the Old Testament Hebrew prophet who is considered the most important prophet in Judaism and one of the most important prophets in Christianity and other religions.",
        "id": "person_115"
      },
      {
        "name": "JesusChrist",
        "birth": "",
        "death": "",
        "description": "The central figure of Christianity; a first-century Jewish preacher and religious leader.",
        "id": "person_951"
      }
    ]
  },
  "70": {
    "places": [
      {
        "name": "Mediterranean Sea",
        "description": "Connected to the Atlantic Ocean and almost completely surrounded by land.",
        "id": "place_1191"
      }
    ]
  },
  "71": {},
  "72": {},
  "73": {
    "persons": [
      {
        "name": "JesusChrist",
        "birth": "",
        "death": "",
        "description": "The central figure of Christianity; a first-century Jewish preacher and religious leader.",
        "id": "person_951"
      }
    ]
  },
  "74": {},
  "75": {
    "persons": [
      {
        "name": "Philalethes",
        "birth": null,
        "death": null,
        "description": "A fictional character in Humphry Davy's Consolations in Travel (1830).",
        "id": "person_102"
      },
      {
        "name": "Onuphrio",
        "birth": null,
        "death": null,
        "description": "Onuphiro is the name of a fictional character in the dialogues of Davy's Consolations in Travel. The anglicized version of the name is Humphry.",
        "id": "person_108"
      }
    ]
  },
  "76": {
    "persons": [
      {
        "name": "Ambrosio",
        "birth": null,
        "death": null,
        "description": "A fictional character in Humphry Davy's Consolations in Travel (1830).",
        "id": "person_101"
      }
    ]
  },
  "77": {},
  "78": {
    "persons": [
      {
        "name": "Ambrosio",
        "birth": null,
        "death": null,
        "description": "A fictional character in Humphry Davy's Consolations in Travel (1830).",
        "id": "person_101"
      },
      {
        "name": "JesusChrist",
        "birth": "",
        "death": "",
        "description": "The central figure of Christianity; a first-century Jewish preacher and religious leader.",
        "id": "person_951"
      }
    ]
  },
  "79": {},
  "80": {
    "places": [
      {
        "name": "Africa",
        "description": "The world's second-largest and second-most populous continent.",
        "id": "place_222"
      },
      {
        "name": "Orkney",
        "description": "An archipelago off the northeastern coast of Scotland.",
        "id": "place_940"
      }
    ]
  },
  "81": {
    "persons": [
      {
        "name": "Ambrosio",
        "birth": null,
        "death": null,
        "description": "A fictional character in Humphry Davy's Consolations in Travel (1830).",
        "id": "person_101"
      }
    ]
  },
  "82": {},
  "83": {
    "persons": [
      {
        "name": "Philalethes",
        "birth": null,
        "death": null,
        "description": "A fictional character in Humphry Davy's Consolations in Travel (1830).",
        "id": "person_102"
      },
      {
        "name": "Ambrosio",
        "birth": null,
        "death": null,
        "description": "A fictional character in Humphry Davy's Consolations in Travel (1830).",
        "id": "person_101"
      }
    ]
  },
  "84": {},
  "85": {},
  "86": {
    "persons": [
      {
        "name": "Philalethes",
        "birth": null,
        "death": null,
        "description": "A fictional character in Humphry Davy's Consolations in Travel (1830).",
        "id": "person_102"
      },
      {
        "name": "Ambrosio",
        "birth": null,
        "death": null,
        "description": "A fictional character in Humphry Davy's Consolations in Travel (1830).",
        "id": "person_101"
      }
    ]
  },
  "87": {},
  "88": {
    "persons": [
      {
        "name": "Onuphrio",
        "birth": null,
        "death": null,
        "description": "Onuphiro is the name of a fictional character in the dialogues of Davy's Consolations in Travel. The anglicized version of the name is Humphry.",
        "id": "person_108"
      }
    ]
  },
  "89": {},
  "90": {
    "persons": [
      {
        "name": "Onuphrio",
        "birth": null,
        "death": null,
        "description": "Onuphiro is the name of a fictional character in the dialogues of Davy's Consolations in Travel. The anglicized version of the name is Humphry.",
        "id": "person_108"
      },
      {
        "name": "Ambrosio",
        "birth": null,
        "death": null,
        "description": "A fictional character in Humphry Davy's Consolations in Travel (1830).",
        "id": "person_101"
      }
    ]
  },
  "91": {
    "persons": [
      {
        "name": "Ambrosio",
        "birth": null,
        "death": null,
        "description": "A fictional character in Humphry Davy's Consolations in Travel (1830).",
        "id": "person_101"
      }
    ]
  },
  "92": {},
  "93": {
    "persons": [
      {
        "name": "Onuphrio",
        "birth": null,
        "death": null,
        "description": "Onuphiro is the name of a fictional character in the dialogues of Davy's Consolations in Travel. The anglicized version of the name is Humphry.",
        "id": "person_108"
      },
      {
        "name": "Ambrosio",
        "birth": null,
        "death": null,
        "description": "A fictional character in Humphry Davy's Consolations in Travel (1830).",
        "id": "person_101"
      }
    ]
  },
  "94": {},
  "95": {
    "persons": [
      {
        "name": "Onuphrio",
        "birth": null,
        "death": null,
        "description": "Onuphiro is the name of a fictional character in the dialogues of Davy's Consolations in Travel. The anglicized version of the name is Humphry.",
        "id": "person_108"
      }
    ]
  },
  "96": {
    "persons": [
      {
        "name": "Ambrosio",
        "birth": null,
        "death": null,
        "description": "A fictional character in Humphry Davy's Consolations in Travel (1830).",
        "id": "person_101"
      }
    ],
    "works": [
      {
        "name": "Consolations in Travel, or the Last Days of Philosopher",
        "author": "Humphry Davy",
        "id": "otherwork_037"
      }
    ]
  },
  "97": {},
  "99": {
    "places": [
      {
        "name": "Naples",
        "description": "Naples is the regional capital of Campania in Italy. It is located beneath the volcano, Vesuvius.",
        "id": "place_156"
      }
    ],
    "works": [
      {
        "name": "Consolations in Travel, or the Last Days of Philosopher",
        "author": "Humphry Davy",
        "id": "otherwork_038"
      }
    ]
  },
  "100": {
    "places": [
      {
        "name": "Italy",
        "description": "",
        "id": "place_097"
      }
    ]
  },
  "101": {
    "places": [
      {
        "name": "Naples",
        "description": "Naples is the regional capital of Campania in Italy. It is located beneath the volcano, Vesuvius.",
        "id": "place_156"
      },
      {
        "name": "Paestum",
        "description": "Paestum was an ancient Greek city on the coast of southern Italy.",
        "id": "place_180"
      },
      {
        "name": "Eboli",
        "description": "An Italian town in the province of Salerno.",
        "id": "place_1032"
      }
    ]
  },
  "102": {
    "places": [
      {
        "name": "Salerno",
        "description": "City in south-western Italy, located on the Gulf of Salerno. Salerno is the capital city of the Italian province also named Salerno, in the Campania region of Italy.",
        "id": "place_711"
      }
    ]
  },
  "103": {
    "places": [
      {
        "name": "Sorrento",
        "description": "A coastal town in southwestern Italy.",
        "id": "place_1202"
      },
      {
        "name": "Bay of Naples",
        "description": "The Bay (or Gulf) of Naples is located on the south-western coast of Italy, with Naples to the north, Vesuvius to the east, and the Sorrento Peninsula to the south.",
        "id": "place_704"
      }
    ]
  },
  "104": {
    "places": [
      {
        "name": "Paestum",
        "description": "Paestum was an ancient Greek city on the coast of southern Italy.",
        "id": "place_180"
      },
      {
        "name": "Tyrrhenian Sea",
        "description": "Part of the Mediterranean Sea off the western coast of Italy.",
        "id": "place_1142"
      }
    ]
  },
  "105": {},
  "106": {},
  "107": {},
  "108": {},
  "109": {},
  "110": {},
  "111": {},
  "112": {},
  "113": {},
  "114": {},
  "115": {},
  "116": {},
  "117": {
    "places": [
      {
        "name": "Italy",
        "description": "",
        "id": "place_097"
      }
    ]
  },
  "118": {
    "persons": [
      {
        "name": "Ambrosio",
        "birth": null,
        "death": null,
        "description": "A fictional character in Humphry Davy's Consolations in Travel (1830).",
        "id": "person_101"
      }
    ],
    "places": [
      {
        "name": "Paestum",
        "description": "Paestum was an ancient Greek city on the coast of southern Italy.",
        "id": "place_180"
      }
    ]
  },
  "119": {
    "places": [
      {
        "name": "River Sillaro",
        "description": "A river in Italy.",
        "id": "place_1203"
      }
    ]
  },
  "120": {},
  "121": {},
  "122": {},
  "123": {},
  "124": {},
  "125": {
    "places": [
      {
        "name": "Paestum",
        "description": "Paestum was an ancient Greek city on the coast of southern Italy.",
        "id": "place_180"
      }
    ]
  },
  "126": {
    "persons": [
      {
        "name": "Ambrosio",
        "birth": null,
        "death": null,
        "description": "A fictional character in Humphry Davy's Consolations in Travel (1830).",
        "id": "person_101"
      }
    ]
  },
  "127": {},
  "128": {},
  "129": {},
  "130": {
    "persons": [
      {
        "name": "Onuphrio",
        "birth": null,
        "death": null,
        "description": "Onuphiro is the name of a fictional character in the dialogues of Davy's Consolations in Travel. The anglicized version of the name is Humphry.",
        "id": "person_108"
      }
    ]
  },
  "131": {
    "places": [
      {
        "name": "Italy",
        "description": "",
        "id": "place_097"
      }
    ]
  },
  "132": {},
  "133": {
    "places": [
      {
        "name": "Lipari",
        "description": "A commune including six of seven islands of the Aeolian Islands located in the Tyrrhenian Sea off the northern coast of Sicily in southern Italy.",
        "id": "place_408"
      },
      {
        "name": "Italy",
        "description": "",
        "id": "place_097"
      },
      {
        "name": "Rome",
        "description": "The capital of Italy.",
        "id": "place_155"
      },
      {
        "name": "Mount Etna",
        "description": "Mount Etna, or simply Etna, is an active stratovolcano on the east coast of Sicily, Italy.",
        "id": "place_184"
      },
      {
        "name": "Stromboli",
        "description": "an island in the Tyrrhenian Sea, off the north coast of Sicily, containing Mount Stromboli, one of the four active volcanoes in Italy. It is one of the seven Aeolian Islands, a volcanic arc north of Sicily.",
        "id": "place_1174"
      }
    ]
  },
  "134": {
    "places": [
      {
        "name": "Italy",
        "description": "",
        "id": "place_097"
      },
      {
        "name": "Po Valley",
        "description": "A vast plain area in Northern Italy, featuring the Po River.",
        "id": "place_1204"
      }
    ]
  },
  "135": {
    "places": [
      {
        "name": "Alps",
        "description": "The Alps are the highest and most extensive mountain range that lies entirely in Europe. They are located in eight European countries.",
        "id": "place_247"
      },
      {
        "name": "Terni",
        "description": "Terni is a city in the southern portion of the region of Umbria in central Italy.",
        "id": "place_565"
      },
      {
        "name": "Velino",
        "description": "A river in central Italy, a tributary of the Nera.",
        "id": "place_848"
      },
      {
        "name": "Po Valley",
        "description": "A vast plain area in Northern Italy, featuring the Po River.",
        "id": "place_1204"
      }
    ]
  },
  "136": {
    "places": [
      {
        "name": "Aniene River",
        "description": "The Aniene is a river rising in the Apennines and flowing west to join the Tiber in northern Rome. It is famous for the Tivoli waterfall.",
        "id": "place_527"
      },
      {
        "name": "Aniene",
        "description": "A river that originates in the Appenines in Italy, formerly called the Teverone.",
        "id": "place_1205"
      },
      {
        "name": "Velino",
        "description": "A river in central Italy, a tributary of the Nera.",
        "id": "place_848"
      }
    ]
  },
  "137": {
    "persons": [
      {
        "name": "Ambrosio",
        "birth": null,
        "death": null,
        "description": "A fictional character in Humphry Davy's Consolations in Travel (1830).",
        "id": "person_101"
      }
    ],
    "places": [
      {
        "name": "Solfatara Caldera",
        "description": "Solfatara di Pozzuoli is a volcanic crater near Naples. Though a dormant volcano, it emits jets of steam and sulphurous fumes.",
        "id": "place_528"
      },
      {
        "name": "Albulae Aquae",
        "description": "White Waters'; a group of springs to the west of Tivolo, Italy, and location of an ancient Roman settlement.",
        "id": "place_179"
      },
      {
        "name": "Campagna",
        "description": "The Roman Campagna is an area of low-lying countryside surrounding Rome, where both the Tiber and Aniene Rivers flow.",
        "id": "place_612"
      },
      {
        "name": "Tivoli, Lazio",
        "description": "Tivoli is a town north east of Rome and known for the waterfall on the Aniene River.",
        "id": "place_529"
      }
    ]
  },
  "138": {},
  "139": {}
}